tdk/__init__.py
tdk/__version__.py
tdk/cli.py
tdk/constants.py
tdk/core.py
tdk/exceptions.py
tdk-1.2.0.dist-info/METADATA
tdk-1.2.0.dist-info/RECORD
tdk-1.2.0.dist-info/WHEEL
tdk-1.2.0.dist-info/entry_points.txt
tdk-1.2.0.dist-info/top_level.txt
