Metadata-Version: 2.1
Name: tdk
Version: 1.2.0
Summary: A library for official Turkish dictionary.
Home-page: https://github.com/efe/tdk
Author: Efe Öge
Author-email: efeoge@gmail.com
License: MIT
Platform: UNKNOWN
Classifier: License :: OSI Approved :: MIT License
Classifier: Programming Language :: Python
Classifier: Programming Language :: Python :: 3
Requires-Python: >=3.4.2
